ses_sns_tracker/__init__.py
ses_sns_tracker/admin.py
ses_sns_tracker/apps.py
ses_sns_tracker/backends.py
ses_sns_tracker/managers.py
ses_sns_tracker/migrations/0001_initial.py
ses_sns_tracker/migrations/0002_alter_sesmaildelivery_options.py
ses_sns_tracker/migrations/0003_auto_20220322_0945.py
ses_sns_tracker/migrations/0004_alter_sesmaildelivery_id.py
ses_sns_tracker/migrations/__init__.py
ses_sns_tracker/models.py
ses_sns_tracker/signals.py
ses_sns_tracker/urls.py
ses_sns_tracker/views.py
django_ses_sns_tracker-4.0.0.dist-info/LICENSE
django_ses_sns_tracker-4.0.0.dist-info/METADATA
django_ses_sns_tracker-4.0.0.dist-info/WHEEL
django_ses_sns_tracker-4.0.0.dist-info/RECORD
