Metadata-Version: 2.1
Name: django-ses-sns-tracker
Version: 4.0.0
Summary: Simple wrapper around django-ses to receive and persist sns event data
Home-page: https://github.com/anfema/django-ses-sns-tracker
License: MIT
Author: anfema GmbH
Author-email: contact@anfe.ma
Requires-Python: >=3.8,<4.0
Classifier: Framework :: Django :: 3.2
Classifier: Framework :: Django :: 4.2
Classifier: License :: OSI Approved :: MIT License
Classifier: Operating System :: OS Independent
Classifier: Programming Language :: Python :: 3
Classifier: Programming Language :: Python :: 3.8
Classifier: Programming Language :: Python :: 3.9
Classifier: Programming Language :: Python :: 3.10
Classifier: Programming Language :: Python :: 3.11
Classifier: Programming Language :: Python :: 3.12
Provides-Extra: cryptography
Requires-Dist: django-ses[events] (>=3.5.2,<4.0.0)
Requires-Dist: requests
Requires-Dist: typing_extensions
Project-URL: Repository, https://github.com/anfema/django-ses-sns-tracker
